llmtopic/__init__.py
llmtopic/llmtopic.py
llmtopic-0.0.3.dist-info/METADATA
llmtopic-0.0.3.dist-info/WHEEL
llmtopic-0.0.3.dist-info/top_level.txt
llmtopic-0.0.3.dist-info/RECORD
