Metadata-Version: 2.1
Name: llmtopic
Version: 0.0.3
Summary: A library for extracting topics from text documents using llms.
Author-email: Daniel Klitzke <daniel.klitzke@renumics.com>
Project-URL: Homepage, https://github.com/dani2112/llmtopic
Project-URL: Bug Tracker, https://github.com/dani2112/llmtopic/issues
Classifier: Programming Language :: Python :: 3
Classifier: License :: OSI Approved :: MIT License
Classifier: Operating System :: OS Independent
Requires-Python: >=3.7
Requires-Dist: llama-cpp-python >=0.2.39
Requires-Dist: guidance >=0.1.10
Requires-Dist: sentence-transformers >=2.3.1
Requires-Dist: hnne >=0.1.10
Requires-Dist: tqdm >=4.66.1
Requires-Dist: pyarrow >=15.0.0
Requires-Dist: pandas >=2.2.0
